peerfinder/__init__.py
peerfinder/peerfinder.py
peerfinder-2020.9.5.dist-info/LICENSE
peerfinder-2020.9.5.dist-info/METADATA
peerfinder-2020.9.5.dist-info/WHEEL
peerfinder-2020.9.5.dist-info/entry_points.txt
peerfinder-2020.9.5.dist-info/top_level.txt
peerfinder-2020.9.5.dist-info/RECORD
