Metadata-Version: 2.1
Name: peerfinder
Version: 2020.9.5
Summary: A tool to find common IX points on PeeringDB
Home-page: https://github.com/rucarrol/PeerFinder
Author: Ruairi Carroll
Author-email: ruairi.carroll@gmail.com
License: MIT
Platform: UNKNOWN
Classifier: Programming Language :: Python :: 3
Classifier: Development Status :: 4 - Beta
Classifier: Environment :: Console
Classifier: License :: OSI Approved :: MIT License
Classifier: Operating System :: OS Independent
Requires-Dist: argparse
Requires-Dist: prettytable
Requires-Dist: requests
